pyMFD/FV.py
pyMFD/__init__.py
pyMFD/cantilever.py
pyMFD/nanoscope.py
pyMFD/scan_params.py
pyMFD/summarize.py
pyMFD/tests/__init__.py
pyMFD/tests/test_FV.py
pyMFD/tests/test_cantilever.py
pyMFD/tests/test_nanoscope.py
pyMFD/tests/test_scan_params.py
pymfd-1.0.0.dist-info/METADATA
pymfd-1.0.0.dist-info/WHEEL
pymfd-1.0.0.dist-info/licenses/LICENSE
pymfd-1.0.0.dist-info/RECORD
