Metadata-Version: 2.1
Name: pyMFD
Version: 1.0.0
Summary: pyMFD is a tool to analyze atomic force microscope force-volume data of microcantilevers in order to extract Young's modulus.
Project-URL: Homepage, https://github.com/larsenkg/pyMFD
Project-URL: Bug Tracker, https://github.com/larsenkg/pyMFD/issues
Author-email: Kyle Larsen <larsenkg@gmail.com>
License: Copyright 2022 Kyle G. Larsen
Classifier: Intended Audience :: Science/Research
Classifier: License :: OSI Approved :: MIT License
Classifier: Operating System :: OS Independent
Classifier: Programming Language :: Python :: 3
Classifier: Topic :: Scientific/Engineering :: Physics
Requires-Python: >=3.7
Requires-Dist: bottleneck>=1.3.2
Requires-Dist: matplotlib>=3.5.0
Requires-Dist: numpy>=1.21.2
Requires-Dist: scipy>=1.7.1
Provides-Extra: tests
Requires-Dist: pytest>=7.1.2; extra == 'tests'
